rabbitmqtesttool/__init__.py
rabbitmqtesttool/commandline.py
rabbitmqtesttool/connection.py
rabbitmqtesttool/main.py
RabbitMQ_Test_Tool-1.1.7.dist-info/LICENSE
RabbitMQ_Test_Tool-1.1.7.dist-info/METADATA
RabbitMQ_Test_Tool-1.1.7.dist-info/WHEEL
RabbitMQ_Test_Tool-1.1.7.dist-info/entry_points.txt
RabbitMQ_Test_Tool-1.1.7.dist-info/top_level.txt
RabbitMQ_Test_Tool-1.1.7.dist-info/RECORD
