Metadata-Version: 2.1
Name: RabbitMQ Test Tool
Version: 1.1.7
Summary: A simple test script to test a RabbitMQ cluster
Home-page: UNKNOWN
Author: Nicolas Bock
License: UNKNOWN
Platform: UNKNOWN
License-File: LICENSE
